setup.py
wikia_dstk/__init__.py
wikia_dstk.egg-info/PKG-INFO
wikia_dstk.egg-info/SOURCES.txt
wikia_dstk.egg-info/dependency_links.txt
wikia_dstk.egg-info/requires.txt
wikia_dstk.egg-info/top_level.txt
wikia_dstk/authority/__init__.py
wikia_dstk/authority/add_author_authority.py
wikia_dstk/authority/add_topics_totals.py
wikia_dstk/authority/client.py
wikia_dstk/authority/create_database.py
wikia_dstk/authority/fix_topics.py
wikia_dstk/authority/pageviews_into_database.py
wikia_dstk/authority/scale_authority_globally.py
wikia_dstk/knowledge_graph/__init__.py
wikia_dstk/knowledge_graph/dependencies_to_graph.py
wikia_dstk/knowledge_graph/dependencies_to_graph_worker.py
wikia_dstk/knowledge_graph/download_parses.py
wikia_dstk/knowledge_graph/infoboxes_to_graph.py
wikia_dstk/knowledge_graph/videos_to_graph.py
wikia_dstk/lda/__init__.py
wikia_dstk/lda/csv_lda_client.py
wikia_dstk/lda/csv_lda_server.py
wikia_dstk/lda/name_lda_topics.py
wikia_dstk/lda/page_lda_client.py
wikia_dstk/lda/page_lda_fromfile.py
wikia_dstk/lda/page_lda_predictor.py
wikia_dstk/lda/page_lda_server.py
wikia_dstk/lda/video_lda_client.py
wikia_dstk/lda/video_lda_server.py
wikia_dstk/lda/wiki_lda_client.py
wikia_dstk/lda/wiki_lda_server.py
wikia_dstk/loadbalancing/__init__.py
wikia_dstk/pipeline/__init__.py
wikia_dstk/pipeline/data_extraction/__init__.py
wikia_dstk/pipeline/data_extraction/child.py
wikia_dstk/pipeline/data_extraction/config.py
wikia_dstk/pipeline/data_extraction/monitor.py
wikia_dstk/pipeline/data_extraction/run.py
wikia_dstk/pipeline/event/__init__.py
wikia_dstk/pipeline/event/get_text.py
wikia_dstk/pipeline/event/send_batch.py
wikia_dstk/pipeline/event/write.py
wikia_dstk/pipeline/parser/__init__.py
wikia_dstk/pipeline/parser/config.py
wikia_dstk/pipeline/parser/monitor.py
wikia_dstk/pipeline/parser/run.py
wikia_dstk/pipeline/wiki_data_extraction/__init__.py
wikia_dstk/pipeline/wiki_data_extraction/child.py
wikia_dstk/pipeline/wiki_data_extraction/config.py
wikia_dstk/pipeline/wiki_data_extraction/launch.py
wikia_dstk/pipeline/wiki_data_extraction/run.py
wikia_dstk/recommendations/__init__.py
wikia_dstk/recommendations/client.py
