Metadata-Version: 1.0
Name: wikia-dstk
Version: 0.0.2
Summary: A library for automated data science scripts that rely on NLP libs, etc.
Home-page: https://github.com/Wikia/data-science-toolkit
Author: Robert Elwell
Author-email: robert.elwell@gmail.com
License: Other
Platform: UNKNOWN
